[{
  "Country": "United States of America",
  "TradeValue": 2937064484,
  "TradeBalance": -1183123078,
  "AnnualGrowth": 22,
  "WorldShare": 13.4,
  "EaseBusinessRank": 6,
  "Index": 1,
  "zhName": "美国",
  "iso2Code": "US"
}, {
  "Country": "China",
  "TradeValue": 2438686293,
  "TradeBalance": 587547398,
  "AnnualGrowth": 19,
  "WorldShare": 11.1,
  "EaseBusinessRank": 31,
  "Index": 2,
  "zhName": "中国",
  "iso2Code": "CN"
}, {
  "Country": "Germany",
  "TradeValue": 1421195357,
  "TradeBalance": 205192436,
  "AnnualGrowth": 21,
  "WorldShare": 6.5,
  "EaseBusinessRank": 22,
  "Index": 3,
  "zhName": "德国",
  "iso2Code": "DE"
}, {
  "Country": "Japan",
  "TradeValue": 772678811,
  "TradeBalance": -15217866,
  "AnnualGrowth": 22,
  "WorldShare": 3.5,
  "EaseBusinessRank": 29,
  "Index": 4,
  "zhName": "日本",
  "iso2Code": "JP"
}, {
  "Country": "Hong Kong, China",
  "TradeValue": 713969246,
  "TradeBalance": -41815266,
  "AnnualGrowth": 25,
  "WorldShare": 3.3,
  "EaseBusinessRank": 3,
  "Index": 5,
  "zhName": "中国香港",
  "iso2Code": "CN"
}, {
  "Country": "France",
  "TradeValue": 701907963,
  "TradeBalance": -132428300,
  "AnnualGrowth": 23,
  "WorldShare": 3.2,
  "EaseBusinessRank": 32,
  "Index": 6,
  "zhName": "法国",
  "iso2Code": "FR"
}, {
  "Country": "United Kingdom",
  "TradeValue": 689698807,
  "TradeBalance": -221639701,
  "AnnualGrowth": 9,
  "WorldShare": 3.2,
  "EaseBusinessRank": 8,
  "Index": 7,
  "zhName": "英国",
  "iso2Code": "GB"
}, {
  "Country": "Netherlands",
  "TradeValue": 620789797,
  "TradeBalance": 71036845,
  "AnnualGrowth": 28,
  "WorldShare": 2.8,
  "EaseBusinessRank": 42,
  "Index": 8,
  "zhName": "荷兰",
  "iso2Code": "NL"
}, {
  "Country": "Korea",
  "TradeValue": 615034495,
  "TradeBalance": 29404127,
  "AnnualGrowth": 32,
  "WorldShare": 2.8,
  "EaseBusinessRank": 5,
  "Index": 9,
  "zhName": "韩国",
  "iso2Code": "KR"
}, {
  "Country": "India",
  "TradeValue": 570402004,
  "TradeBalance": -175588331,
  "AnnualGrowth": 55,
  "WorldShare": 2.6,
  "EaseBusinessRank": 63,
  "Index": 10,
  "zhName": "印度",
  "iso2Code": "IN"
}, {
  "Country": "Italy",
  "TradeValue": 551533459,
  "TradeBalance": 59476093,
  "AnnualGrowth": 29,
  "WorldShare": 2.5,
  "EaseBusinessRank": 58,
  "Index": 11,
  "zhName": "意大利",
  "iso2Code": "IT"
}, {
  "Country": "Belgium",
  "TradeValue": 516585831,
  "TradeBalance": 30951541,
  "AnnualGrowth": 30,
  "WorldShare": 2.4,
  "EaseBusinessRank": 46,
  "Index": 12,
  "zhName": "比利时",
  "iso2Code": "BE"
}, {
  "Country": "Mexico",
  "TradeValue": 506565459,
  "TradeBalance": -11969956,
  "AnnualGrowth": 32,
  "WorldShare": 2.3,
  "EaseBusinessRank": 60,
  "Index": 13,
  "zhName": "墨西哥",
  "iso2Code": "MX"
}, {
  "Country": "Canada",
  "TradeValue": 489582673,
  "TradeBalance": 14143331,
  "AnnualGrowth": 21,
  "WorldShare": 2.2,
  "EaseBusinessRank": 23,
  "Index": 14,
  "zhName": "加拿大",
  "iso2Code": "CA"
}, {
  "Country": "Spain",
  "TradeValue": 426059817,
  "TradeBalance": -34501298,
  "AnnualGrowth": 29,
  "WorldShare": 1.9,
  "EaseBusinessRank": 30,
  "Index": 15,
  "zhName": "西班牙",
  "iso2Code": "ES"
}, {
  "Country": "Singapore",
  "TradeValue": 406912769,
  "TradeBalance": 50837197,
  "AnnualGrowth": 24,
  "WorldShare": 1.9,
  "EaseBusinessRank": 2,
  "Index": 16,
  "zhName": "新加坡",
  "iso2Code": "SG"
}, {
  "Country": "Taipei, Chinese",
  "TradeValue": 382498457,
  "TradeBalance": 65066611,
  "AnnualGrowth": 33,
  "WorldShare": 1.7,
  "EaseBusinessRank": 15,
  "Index": 17,
  "zhName": "中国台湾省",
  "iso2Code": "CN"
}, {
  "Country": "Poland",
  "TradeValue": 335451322,
  "TradeBalance": -17619197,
  "AnnualGrowth": 32,
  "WorldShare": 1.5,
  "EaseBusinessRank": 40,
  "Index": 18,
  "zhName": "波兰",
  "iso2Code": "PL"
}, {
  "Country": "Viet Nam",
  "TradeValue": 329199261,
  "TradeBalance": 77556653,
  "AnnualGrowth": 17,
  "WorldShare": 1.5,
  "EaseBusinessRank": 70,
  "Index": 19,
  "zhName": "越南",
  "iso2Code": "VN"
}, {
  "Country": "Switzerland",
  "TradeValue": 323063106,
  "TradeBalance": 57180618,
  "AnnualGrowth": 11,
  "WorldShare": 1.5,
  "EaseBusinessRank": 36,
  "Index": 20,
  "zhName": "瑞士",
  "iso2Code": "CH"
}, {
  "Country": "Russian Federation",
  "TradeValue": 293501672,
  "TradeBalance": 198812667,
  "AnnualGrowth": 27,
  "WorldShare": 1.3,
  "EaseBusinessRank": 28,
  "Index": 21,
  "zhName": "俄罗斯",
  "iso2Code": "RU"
}, {
  "Country": "Turkey",
  "TradeValue": 271422758,
  "TradeBalance": -46158444,
  "AnnualGrowth": 24,
  "WorldShare": 1.2,
  "EaseBusinessRank": 33,
  "Index": 22,
  "zhName": "土耳其",
  "iso2Code": "TR"
}, {
  "Country": "Thailand",
  "TradeValue": 269102030,
  "TradeBalance": -1609614,
  "AnnualGrowth": 29,
  "WorldShare": 1.2,
  "EaseBusinessRank": 21,
  "Index": 23,
  "zhName": "泰国",
  "iso2Code": "TH"
}, {
  "Country": "Australia",
  "TradeValue": 248893435,
  "TradeBalance": 96706503,
  "AnnualGrowth": 23,
  "WorldShare": 1.1,
  "EaseBusinessRank": 14,
  "Index": 24,
  "zhName": "澳大利亚",
  "iso2Code": "AU"
}, {
  "Country": "Malaysia",
  "TradeValue": 238321107,
  "TradeBalance": 60967286,
  "AnnualGrowth": 26,
  "WorldShare": 1.1,
  "EaseBusinessRank": 12,
  "Index": 25,
  "zhName": "马来西亚",
  "iso2Code": "MY"
}, {
  "Country": "Brazil",
  "TradeValue": 219408049,
  "TradeBalance": 61406528,
  "AnnualGrowth": 38,
  "WorldShare": 1,
  "EaseBusinessRank": 124,
  "Index": 26,
  "zhName": "巴西",
  "iso2Code": "BR"
}, {
  "Country": "Austria",
  "TradeValue": 219263720,
  "TradeBalance": -16335814,
  "AnnualGrowth": 27,
  "WorldShare": 1,
  "EaseBusinessRank": 27,
  "Index": 27,
  "zhName": "奥地利",
  "iso2Code": "AT"
}, {
  "Country": "Czech Republic",
  "TradeValue": 208951668,
  "TradeBalance": 16623227,
  "AnnualGrowth": 22,
  "WorldShare": 1,
  "EaseBusinessRank": 41,
  "Index": 28,
  "zhName": "捷克",
  "iso2Code": "CZ"
}, {
  "Country": "United Arab Emirates",
  "TradeValue": 196871418,
  "TradeBalance": 20871148,
  "AnnualGrowth": 26,
  "WorldShare": 0.9,
  "EaseBusinessRank": 16,
  "Index": 29,
  "zhName": "阿联酋",
  "iso2Code": "AE"
}, {
  "Country": "Indonesia",
  "TradeValue": 195712409,
  "TradeBalance": 32518755,
  "AnnualGrowth": 38,
  "WorldShare": 0.9,
  "EaseBusinessRank": 73,
  "Index": 30,
  "zhName": "印度尼西亚",
  "iso2Code": "ID"
}, {
  "Country": "Sweden",
  "TradeValue": 187067834,
  "TradeBalance": 2748386,
  "AnnualGrowth": 25,
  "WorldShare": 0.9,
  "EaseBusinessRank": 10,
  "Index": 31,
  "zhName": "瑞典",
  "iso2Code": "SE"
}, {
  "Country": "Saudi Arabia",
  "TradeValue": 152333959,
  "TradeBalance": 115212888,
  "AnnualGrowth": 16,
  "WorldShare": 0.7,
  "EaseBusinessRank": 62,
  "Index": 32,
  "zhName": "沙特阿拉伯",
  "iso2Code": "SA"
}, {
  "Country": "Hungary",
  "TradeValue": 138904664,
  "TradeBalance": 2352072,
  "AnnualGrowth": 22,
  "WorldShare": 0.6,
  "EaseBusinessRank": 52,
  "Index": 33,
  "zhName": "匈牙利",
  "iso2Code": "HU"
}, {
  "Country": "Philippines",
  "TradeValue": 124386497,
  "TradeBalance": -49766774,
  "AnnualGrowth": 37,
  "WorldShare": 0.6,
  "EaseBusinessRank": 95,
  "Index": 34,
  "zhName": "菲律宾",
  "iso2Code": "PH"
}, {
  "Country": "Denmark",
  "TradeValue": 121784026,
  "TradeBalance": 3230588,
  "AnnualGrowth": 26,
  "WorldShare": 0.6,
  "EaseBusinessRank": 4,
  "Index": 35,
  "zhName": "丹麦",
  "iso2Code": "DK"
}, {
  "Country": "Ireland",
  "TradeValue": 119507355,
  "TradeBalance": 70488950,
  "AnnualGrowth": 20,
  "WorldShare": 0.5,
  "EaseBusinessRank": 24,
  "Index": 36,
  "zhName": "爱尔兰",
  "iso2Code": "IE"
}, {
  "Country": "Romania",
  "TradeValue": 116408053,
  "TradeBalance": -28922070,
  "AnnualGrowth": 27,
  "WorldShare": 0.5,
  "EaseBusinessRank": 55,
  "Index": 37,
  "zhName": "罗马尼亚",
  "iso2Code": "RO"
}, {
  "Country": "Slovakia",
  "TradeValue": 104682098,
  "TradeBalance": -322010,
  "AnnualGrowth": 23,
  "WorldShare": 0.5,
  "EaseBusinessRank": 45,
  "Index": 38,
  "zhName": "斯洛伐克",
  "iso2Code": "SK"
}, {
  "Country": "Norway",
  "TradeValue": 98636184,
  "TradeBalance": 61843562,
  "AnnualGrowth": 21,
  "WorldShare": 0.5,
  "EaseBusinessRank": 9,
  "Index": 39,
  "zhName": "挪威",
  "iso2Code": "NO"
}, {
  "Country": "Portugal",
  "TradeValue": 97594850,
  "TradeBalance": -22520022,
  "AnnualGrowth": 25,
  "WorldShare": 0.4,
  "EaseBusinessRank": 39,
  "Index": 40,
  "zhName": "葡萄牙",
  "iso2Code": "PT"
}, {
  "Country": "South Africa",
  "TradeValue": 93614253,
  "TradeBalance": 30119797,
  "AnnualGrowth": 36,
  "WorldShare": 0.4,
  "EaseBusinessRank": 84,
  "Index": 41,
  "zhName": "南非",
  "iso2Code": "ZA"
}, {
  "Country": "Israel",
  "TradeValue": 90279719,
  "TradeBalance": -30451165,
  "AnnualGrowth": 30,
  "WorldShare": 0.4,
  "EaseBusinessRank": 35,
  "Index": 42,
  "zhName": "以色列",
  "iso2Code": "IL"
}, {
  "Country": "Chile",
  "TradeValue": 87041788,
  "TradeBalance": 2800239,
  "AnnualGrowth": 57,
  "WorldShare": 0.4,
  "EaseBusinessRank": 59,
  "Index": 43,
  "zhName": "智利",
  "iso2Code": "CL"
}, {
  "Country": "Finland",
  "TradeValue": 85992875,
  "TradeBalance": -4666321,
  "AnnualGrowth": 26,
  "WorldShare": 0.4,
  "EaseBusinessRank": 20,
  "Index": 44,
  "zhName": "芬兰",
  "iso2Code": "FI"
}, {
  "Country": "Greece",
  "TradeValue": 74006314,
  "TradeBalance": -27554702,
  "AnnualGrowth": 33,
  "WorldShare": 0.3,
  "EaseBusinessRank": 79,
  "Index": 45,
  "zhName": "希腊",
  "iso2Code": "GR"
}, {
  "Country": "Egypt",
  "TradeValue": 73781229,
  "TradeBalance": -33079525,
  "AnnualGrowth": 22,
  "WorldShare": 0.3,
  "EaseBusinessRank": 114,
  "Index": 46,
  "zhName": "埃及",
  "iso2Code": "EG"
}, {
  "Country": "Pakistan",
  "TradeValue": 73106624,
  "TradeBalance": -44226618,
  "AnnualGrowth": 59,
  "WorldShare": 0.3,
  "EaseBusinessRank": 108,
  "Index": 47,
  "zhName": "巴基斯坦",
  "iso2Code": "PK"
}, {
  "Country": "Ukraine",
  "TradeValue": 69962816,
  "TradeBalance": -4092540,
  "AnnualGrowth": 30,
  "WorldShare": 0.3,
  "EaseBusinessRank": 64,
  "Index": 48,
  "zhName": "乌克兰",
  "iso2Code": "UA"
}, {
  "Country": "Bangladesh",
  "TradeValue": 69752376,
  "TradeBalance": -17294005,
  "AnnualGrowth": 48,
  "WorldShare": 0.3,
  "EaseBusinessRank": 168,
  "Index": 49,
  "zhName": "孟加拉国",
  "iso2Code": "BD"
}, {
  "Country": "Argentina",
  "TradeValue": 63183753,
  "TradeBalance": 14654975,
  "AnnualGrowth": 49,
  "WorldShare": 0.3,
  "EaseBusinessRank": 126,
  "Index": 50,
  "zhName": "阿根廷",
  "iso2Code": "AR"
}, {
  "Country": "Colombia",
  "TradeValue": 61101362,
  "TradeBalance": -20612762,
  "AnnualGrowth": 40,
  "WorldShare": 0.3,
  "EaseBusinessRank": 67,
  "Index": 51,
  "zhName": "哥伦比亚",
  "iso2Code": "CO"
}, {
  "Country": "Morocco",
  "TradeValue": 58667257,
  "TradeBalance": -22088514,
  "AnnualGrowth": 32,
  "WorldShare": 0.3,
  "EaseBusinessRank": 53,
  "Index": 52,
  "zhName": "摩洛哥",
  "iso2Code": "MA"
}, {
  "Country": "Nigeria",
  "TradeValue": 52441679,
  "TradeBalance": -4871258,
  "AnnualGrowth": -1,
  "WorldShare": 0.2,
  "EaseBusinessRank": 131,
  "Index": 53,
  "zhName": "尼日利亚",
  "iso2Code": "NG"
}, {
  "Country": "Peru",
  "TradeValue": 51177743,
  "TradeBalance": 5082372,
  "AnnualGrowth": 42,
  "WorldShare": 0.2,
  "EaseBusinessRank": 76,
  "Index": 54,
  "zhName": "秘鲁",
  "iso2Code": "PE"
}, {
  "Country": "Slovenia",
  "TradeValue": 49607332,
  "TradeBalance": -2833975,
  "AnnualGrowth": 36,
  "WorldShare": 0.2,
  "EaseBusinessRank": 37,
  "Index": 55,
  "zhName": "斯洛文尼亚",
  "iso2Code": "SI"
}, {
  "Country": "New Zealand",
  "TradeValue": 49589283,
  "TradeBalance": -6227425,
  "AnnualGrowth": 34,
  "WorldShare": 0.2,
  "EaseBusinessRank": 1,
  "Index": 56,
  "zhName": "新西兰",
  "iso2Code": "NZ"
}, {
  "Country": "Bulgaria",
  "TradeValue": 47450654,
  "TradeBalance": -5507618,
  "AnnualGrowth": 36,
  "WorldShare": 0.2,
  "EaseBusinessRank": 61,
  "Index": 57,
  "zhName": "保加利亚",
  "iso2Code": "BG"
}, {
  "Country": "Kazakhstan",
  "TradeValue": 45623014,
  "TradeBalance": 11182880,
  "AnnualGrowth": 13,
  "WorldShare": 0.2,
  "EaseBusinessRank": 25,
  "Index": 58,
  "zhName": "哈萨克斯坦",
  "iso2Code": "KZ"
}, {
  "Country": "Lithuania",
  "TradeValue": 44549993,
  "TradeBalance": -3736292,
  "AnnualGrowth": 34,
  "WorldShare": 0.2,
  "EaseBusinessRank": 11,
  "Index": 59,
  "zhName": "立陶宛",
  "iso2Code": "LT"
}, {
  "Country": "Panama",
  "TradeValue": 42960851,
  "TradeBalance": -35460942,
  "AnnualGrowth": 26,
  "WorldShare": 0.2,
  "EaseBusinessRank": 86,
  "Index": 60,
  "zhName": "巴拿马",
  "iso2Code": "PA"
}, {
  "Country": "Belarus",
  "TradeValue": 41810690,
  "TradeBalance": -1921667,
  "AnnualGrowth": 28,
  "WorldShare": 0.2,
  "EaseBusinessRank": 49,
  "Index": 61,
  "zhName": "白俄罗斯",
  "iso2Code": "BY"
}, {
  "Country": "Iraq",
  "TradeValue": 35129335,
  "TradeBalance": 45577743,
  "AnnualGrowth": 9,
  "WorldShare": 0.2,
  "EaseBusinessRank": 172,
  "Index": 62,
  "zhName": "伊拉克",
  "iso2Code": "IQ"
}, {
  "Country": "Croatia",
  "TradeValue": 34495167,
  "TradeBalance": -11715335,
  "AnnualGrowth": 29,
  "WorldShare": 0.2,
  "EaseBusinessRank": 51,
  "Index": 63,
  "zhName": "克罗地亚",
  "iso2Code": "HR"
}, {
  "Country": "Algeria",
  "TradeValue": 34461659,
  "TradeBalance": 2860377,
  "AnnualGrowth": 4,
  "WorldShare": 0.2,
  "EaseBusinessRank": 157,
  "Index": 64,
  "zhName": "阿尔及利亚",
  "iso2Code": "DZ"
}, {
  "Country": "Serbia",
  "TradeValue": 33791355,
  "TradeBalance": -8227828,
  "AnnualGrowth": 29,
  "WorldShare": 0.2,
  "EaseBusinessRank": 44,
  "Index": 65,
  "zhName": "塞尔维亚",
  "iso2Code": "RS"
}, {
  "Country": "Cambodia",
  "TradeValue": 28702890,
  "TradeBalance": -11131107,
  "AnnualGrowth": 49,
  "WorldShare": 0.1,
  "EaseBusinessRank": 144,
  "Index": 66,
  "zhName": "柬埔寨",
  "iso2Code": "KH"
}, {
  "Country": "Dominican Republic",
  "TradeValue": 26942694,
  "TradeBalance": -15111160,
  "AnnualGrowth": 45,
  "WorldShare": 0.1,
  "EaseBusinessRank": 115,
  "Index": 67,
  "zhName": "多米尼加",
  "iso2Code": "DO"
}, {
  "Country": "Guatemala",
  "TradeValue": 26605961,
  "TradeBalance": -13011715,
  "AnnualGrowth": 46,
  "WorldShare": 0.1,
  "EaseBusinessRank": 96,
  "Index": 68,
  "zhName": "危地马拉",
  "iso2Code": "GT"
}, {
  "Country": "Ecuador",
  "TradeValue": 25719892,
  "TradeBalance": 549336,
  "AnnualGrowth": 44,
  "WorldShare": 0.1,
  "EaseBusinessRank": 129,
  "Index": 69,
  "zhName": "厄瓜多尔",
  "iso2Code": "EC"
}, {
  "Country": "Qatar",
  "TradeValue": 25629739,
  "TradeBalance": 52214104,
  "AnnualGrowth": 2,
  "WorldShare": 0.1,
  "EaseBusinessRank": 77,
  "Index": 70,
  "zhName": "卡塔尔",
  "iso2Code": "QA"
}, {
  "Country": "Luxembourg",
  "TradeValue": 25537148,
  "TradeBalance": -9290021,
  "AnnualGrowth": 22,
  "WorldShare": 0.1,
  "EaseBusinessRank": 72,
  "Index": 71,
  "zhName": "卢森堡",
  "iso2Code": "LU"
}, {
  "Country": "Iran, Islamic Republic of",
  "TradeValue": 25165687,
  "TradeBalance": -11233442,
  "AnnualGrowth": 13,
  "WorldShare": 0.1,
  "EaseBusinessRank": 127,
  "Index": 72,
  "zhName": "伊朗",
  "iso2Code": "IR"
}, {
  "Country": "Estonia",
  "TradeValue": 24141188,
  "TradeBalance": -1858496,
  "AnnualGrowth": 36,
  "WorldShare": 0.1,
  "EaseBusinessRank": 18,
  "Index": 73,
  "zhName": "爱沙尼亚",
  "iso2Code": "EE"
}, {
  "Country": "Uzbekistan",
  "TradeValue": 23724275,
  "TradeBalance": -9689298,
  "AnnualGrowth": 19,
  "WorldShare": 0.1,
  "EaseBusinessRank": 69,
  "Index": 74,
  "zhName": "乌兹别克斯坦",
  "iso2Code": "UZ"
}, {
  "Country": "Kuwait",
  "TradeValue": 22993888,
  "TradeBalance": 32583930,
  "AnnualGrowth": 13,
  "WorldShare": 0.1,
  "EaseBusinessRank": 83,
  "Index": 75,
  "zhName": "科威特",
  "iso2Code": "KW"
}, {
  "Country": "Latvia",
  "TradeValue": 22978975,
  "TradeBalance": -3474108,
  "AnnualGrowth": 33,
  "WorldShare": 0.1,
  "EaseBusinessRank": 19,
  "Index": 76,
  "zhName": "拉脱维亚",
  "iso2Code": "LV"
}, {
  "Country": "Tunisia",
  "TradeValue": 21811968,
  "TradeBalance": -5379223,
  "AnnualGrowth": 18,
  "WorldShare": 0.1,
  "EaseBusinessRank": 78,
  "Index": 77,
  "zhName": "突尼斯",
  "iso2Code": "TN"
}, {
  "Country": "Myanmar",
  "TradeValue": 21326734,
  "TradeBalance": -2443043,
  "AnnualGrowth": -16,
  "WorldShare": 0.1,
  "EaseBusinessRank": 165,
  "Index": 78,
  "zhName": "缅甸",
  "iso2Code": "MM"
}, {
  "Country": "Kenya",
  "TradeValue": 19594118,
  "TradeBalance": -12842752,
  "AnnualGrowth": 27,
  "WorldShare": 0.1,
  "EaseBusinessRank": 56,
  "Index": 79,
  "zhName": "肯尼亚",
  "iso2Code": "KE"
}, {
  "Country": "Ghana",
  "TradeValue": 18500854,
  "TradeBalance": -5748889,
  "AnnualGrowth": 20,
  "WorldShare": 0.1,
  "EaseBusinessRank": 118,
  "Index": 80,
  "zhName": "加纳",
  "iso2Code": "GH"
}, {
  "Country": "Oman",
  "TradeValue": 17890612,
  "TradeBalance": 34771053,
  "AnnualGrowth": 6,
  "WorldShare": 0.1,
  "EaseBusinessRank": 68,
  "Index": 81,
  "zhName": "阿曼",
  "iso2Code": "OM"
}, {
  "Country": "Jordan",
  "TradeValue": 17614967,
  "TradeBalance": -9238562,
  "AnnualGrowth": 21,
  "WorldShare": 0.1,
  "EaseBusinessRank": 75,
  "Index": 82,
  "zhName": "约旦",
  "iso2Code": "JO"
}, {
  "Country": "Sri Lanka",
  "TradeValue": 17594479,
  "TradeBalance": -4872680,
  "AnnualGrowth": 27,
  "WorldShare": 0.1,
  "EaseBusinessRank": 99,
  "Index": 83,
  "zhName": "斯里兰卡",
  "iso2Code": "LK"
}, {
  "Country": "Costa Rica",
  "TradeValue": 16756092,
  "TradeBalance": 4620775,
  "AnnualGrowth": 33,
  "WorldShare": 0.1,
  "EaseBusinessRank": 74,
  "Index": 84,
  "zhName": "哥斯达黎加",
  "iso2Code": "CR"
}, {
  "Country": "Liberia",
  "TradeValue": 15857620,
  "TradeBalance": -14228006,
  "AnnualGrowth": 28,
  "WorldShare": 0.1,
  "EaseBusinessRank": 175,
  "Index": 85,
  "zhName": "利比里亚",
  "iso2Code": "LR"
}, {
  "Country": "El Salvador",
  "TradeValue": 15647116,
  "TradeBalance": -9987091,
  "AnnualGrowth": 55,
  "WorldShare": 0.1,
  "EaseBusinessRank": 91,
  "Index": 86,
  "zhName": "萨尔瓦多",
  "iso2Code": "SV"
}, {
  "Country": "Libya, State of",
  "TradeValue": 15535041,
  "TradeBalance": 15105003,
  "AnnualGrowth": 39,
  "WorldShare": 0.1,
  "EaseBusinessRank": 186,
  "Index": 87,
  "zhName": "利比亚",
  "iso2Code": "LY"
}, {
  "Country": "Ethiopia",
  "TradeValue": 15289980,
  "TradeBalance": -12232351,
  "AnnualGrowth": 8,
  "WorldShare": 0.1,
  "EaseBusinessRank": 159,
  "Index": 88,
  "zhName": "埃塞俄比亚",
  "iso2Code": "ET"
}, {
  "Country": "Marshall Islands",
  "TradeValue": 13938946,
  "TradeBalance": -12623693,
  "AnnualGrowth": -7,
  "WorldShare": 0.1,
  "EaseBusinessRank": 153,
  "Index": 89,
  "zhName": "马绍尔群岛",
  "iso2Code": "MH"
}, {
  "Country": "Paraguay",
  "TradeValue": 13559729,
  "TradeBalance": -3012433,
  "AnnualGrowth": 36,
  "WorldShare": 0.1,
  "EaseBusinessRank": 125,
  "Index": 90,
  "zhName": "巴拉圭",
  "iso2Code": "PY"
}, {
  "Country": "Côte d'Ivoire",
  "TradeValue": 13310583,
  "TradeBalance": -652960,
  "AnnualGrowth": 37,
  "WorldShare": 0.1,
  "EaseBusinessRank": 110,
  "Index": 91,
  "zhName": "科特迪瓦",
  "iso2Code": ""
}, {
  "Country": "Bosnia and Herzegovina",
  "TradeValue": 13030086,
  "TradeBalance": -4415975,
  "AnnualGrowth": 32,
  "WorldShare": 0.1,
  "EaseBusinessRank": 90,
  "Index": 92,
  "zhName": "波黑",
  "iso2Code": "BA"
}, {
  "Country": "Uruguay",
  "TradeValue": 12803320,
  "TradeBalance": -1618317,
  "AnnualGrowth": 43,
  "WorldShare": 0.1,
  "EaseBusinessRank": 101,
  "Index": 93,
  "zhName": "乌拉圭",
  "iso2Code": "UY"
}, {
  "Country": "Nepal",
  "TradeValue": 12516490,
  "TradeBalance": -10870490,
  "AnnualGrowth": 56,
  "WorldShare": 0.1,
  "EaseBusinessRank": 94,
  "Index": 94,
  "zhName": "尼泊尔",
  "iso2Code": "NP"
}, {
  "Country": "Lebanon",
  "TradeValue": 12056727,
  "TradeBalance": -9851501,
  "AnnualGrowth": 19,
  "WorldShare": 0.1,
  "EaseBusinessRank": 143,
  "Index": 95,
  "zhName": "黎巴嫩",
  "iso2Code": "LB"
}, {
  "Country": "Azerbaijan",
  "TradeValue": 11698496,
  "TradeBalance": 10508175,
  "AnnualGrowth": 9,
  "WorldShare": 0.1,
  "EaseBusinessRank": 34,
  "Index": 96,
  "zhName": "阿塞拜疆",
  "iso2Code": "AZ"
}, {
  "Country": "Honduras",
  "TradeValue": 11631003,
  "TradeBalance": -6655054,
  "AnnualGrowth": 46,
  "WorldShare": 0.1,
  "EaseBusinessRank": 133,
  "Index": 97,
  "zhName": "洪都拉斯",
  "iso2Code": "HN"
}, {
  "Country": "Angola",
  "TradeValue": 11359681,
  "TradeBalance": 22384113,
  "AnnualGrowth": 22,
  "WorldShare": 0.1,
  "EaseBusinessRank": 177,
  "Index": 98,
  "zhName": "安哥拉",
  "iso2Code": "AO"
}, {
  "Country": "Bahrain",
  "TradeValue": 11205267,
  "TradeBalance": 1008885,
  "AnnualGrowth": 28,
  "WorldShare": 0.1,
  "EaseBusinessRank": 43,
  "Index": 99,
  "zhName": "巴林",
  "iso2Code": "BH"
}, {
  "Country": "Tanzania, United Republic of",
  "TradeValue": 10873264,
  "TradeBalance": -4482401,
  "AnnualGrowth": 28,
  "WorldShare": 0,
  "EaseBusinessRank": 141,
  "Index": 100,
  "zhName": "坦桑尼亚",
  "iso2Code": "TZ"
}, {
  "Country": "Nicaragua",
  "TradeValue": 10163198,
  "TradeBalance": -3668112,
  "AnnualGrowth": 55,
  "WorldShare": 0,
  "EaseBusinessRank": 142,
  "Index": 101,
  "zhName": "尼加拉瓜",
  "iso2Code": "NI"
}, {
  "Country": "Cyprus",
  "TradeValue": 10088630,
  "TradeBalance": -6201759,
  "AnnualGrowth": 16,
  "WorldShare": 0,
  "EaseBusinessRank": 54,
  "Index": 102,
  "zhName": "塞浦路斯",
  "iso2Code": "CY"
}, {
  "Country": "Bolivia, Plurinational State of",
  "TradeValue": 9559086,
  "TradeBalance": 1470927,
  "AnnualGrowth": 35,
  "WorldShare": 0,
  "EaseBusinessRank": 150,
  "Index": 103,
  "zhName": "玻利维亚",
  "iso2Code": "BO"
}, {
  "Country": "Yemen",
  "TradeValue": 9238659,
  "TradeBalance": -7438193,
  "AnnualGrowth": 2,
  "WorldShare": 0,
  "EaseBusinessRank": 187,
  "Index": 104,
  "zhName": "也门",
  "iso2Code": "YE"
}, {
  "Country": "Mozambique",
  "TradeValue": 8622697,
  "TradeBalance": -3511011,
  "AnnualGrowth": 34,
  "WorldShare": 0,
  "EaseBusinessRank": 138,
  "Index": 105,
  "zhName": "莫桑比克",
  "iso2Code": "MZ"
}, {
  "Country": "Brunei Darussalam",
  "TradeValue": 8574827,
  "TradeBalance": 2483357,
  "AnnualGrowth": 61,
  "WorldShare": 0,
  "EaseBusinessRank": 66,
  "Index": 106,
  "zhName": "文莱",
  "iso2Code": "BN"
}, {
  "Country": "Senegal",
  "TradeValue": 8285456,
  "TradeBalance": -3799390,
  "AnnualGrowth": 6,
  "WorldShare": 0,
  "EaseBusinessRank": 123,
  "Index": 107,
  "zhName": "塞内加尔",
  "iso2Code": "SN"
}, {
  "Country": "Congo, Democratic Republic of the",
  "TradeValue": 8238209,
  "TradeBalance": 6382884,
  "AnnualGrowth": 29,
  "WorldShare": 0,
  "EaseBusinessRank": 183,
  "Index": 108,
  "zhName": "",
  "iso2Code": ""
}, {
  "Country": "Iceland",
  "TradeValue": 7841938,
  "TradeBalance": -1865249,
  "AnnualGrowth": 37,
  "WorldShare": 0,
  "EaseBusinessRank": 26,
  "Index": 109,
  "zhName": "冰岛",
  "iso2Code": "IS"
}, {
  "Country": "Georgia",
  "TradeValue": 7697303,
  "TradeBalance": -4405927,
  "AnnualGrowth": 25,
  "WorldShare": 0,
  "EaseBusinessRank": 7,
  "Index": 110,
  "zhName": "格鲁吉亚",
  "iso2Code": "GE"
}, {
  "Country": "Bahamas",
  "TradeValue": 7486183,
  "TradeBalance": -6354455,
  "AnnualGrowth": 27,
  "WorldShare": 0,
  "EaseBusinessRank": 119,
  "Index": 111,
  "zhName": "巴哈马",
  "iso2Code": "BS"
}, {
  "Country": "Cameroon",
  "TradeValue": 7340843,
  "TradeBalance": -2567972,
  "AnnualGrowth": 11,
  "WorldShare": 0,
  "EaseBusinessRank": 167,
  "Index": 112,
  "zhName": "喀麦隆",
  "iso2Code": "CM"
}, {
  "Country": "Venezuela, Bolivarian Republic of",
  "TradeValue": 7248817,
  "TradeBalance": -3956987,
  "AnnualGrowth": 14,
  "WorldShare": 0,
  "EaseBusinessRank": 188,
  "Index": 113,
  "zhName": "",
  "iso2Code": ""
}, {
  "Country": "Moldova, Republic of",
  "TradeValue": 7176839,
  "TradeBalance": -4032363,
  "AnnualGrowth": 33,
  "WorldShare": 0,
  "EaseBusinessRank": 48,
  "Index": 114,
  "zhName": "",
  "iso2Code": ""
}, {
  "Country": "Zambia",
  "TradeValue": 7111525,
  "TradeBalance": 4105992,
  "AnnualGrowth": 32,
  "WorldShare": 0,
  "EaseBusinessRank": 85,
  "Index": 115,
  "zhName": "赞比亚",
  "iso2Code": "ZM"
}, {
  "Country": "Malta",
  "TradeValue": 7075037,
  "TradeBalance": -3874605,
  "AnnualGrowth": 35,
  "WorldShare": 0,
  "EaseBusinessRank": 88,
  "Index": 116,
  "zhName": "马耳他",
  "iso2Code": "MT"
}, {
  "Country": "Albania",
  "TradeValue": 6680050,
  "TradeBalance": -3392426,
  "AnnualGrowth": 30,
  "WorldShare": 0,
  "EaseBusinessRank": 82,
  "Index": 117,
  "zhName": "阿尔巴尼亚",
  "iso2Code": "AL"
}, {
  "Country": "Sudan",
  "TradeValue": 6289677,
  "TradeBalance": -3970344,
  "AnnualGrowth": -11,
  "WorldShare": 0,
  "EaseBusinessRank": 171,
  "Index": 118,
  "zhName": "苏丹",
  "iso2Code": "SD"
}, {
  "Country": "Botswana",
  "TradeValue": 6141718,
  "TradeBalance": -2412843,
  "AnnualGrowth": 28,
  "WorldShare": 0,
  "EaseBusinessRank": 87,
  "Index": 119,
  "zhName": "博茨瓦纳",
  "iso2Code": "BW"
}, {
  "Country": "Mongolia",
  "TradeValue": 6063775,
  "TradeBalance": 1858196,
  "AnnualGrowth": 31,
  "WorldShare": 0,
  "EaseBusinessRank": 81,
  "Index": 120,
  "zhName": "蒙古",
  "iso2Code": "MN"
}, {
  "Country": "Namibia",
  "TradeValue": 5797686,
  "TradeBalance": -1658911,
  "AnnualGrowth": 50,
  "WorldShare": 0,
  "EaseBusinessRank": 104,
  "Index": 121,
  "zhName": "纳米比亚",
  "iso2Code": "NA"
}, {
  "Country": "Kyrgyzstan",
  "TradeValue": 5570126,
  "TradeBalance": -3911177,
  "AnnualGrowth": 51,
  "WorldShare": 0,
  "EaseBusinessRank": 80,
  "Index": 122,
  "zhName": "吉尔吉斯坦",
  "iso2Code": "KG"
}, {
  "Country": "Trinidad and Tobago",
  "TradeValue": 5486782,
  "TradeBalance": 5210584,
  "AnnualGrowth": 9,
  "WorldShare": 0,
  "EaseBusinessRank": 105,
  "Index": 123,
  "zhName": "特立尼达和多巴哥",
  "iso2Code": "TT"
}, {
  "Country": "Lao People's Democratic Republic",
  "TradeValue": 5420341,
  "TradeBalance": 65509,
  "AnnualGrowth": 8,
  "WorldShare": 0,
  "EaseBusinessRank": 154,
  "Index": 124,
  "zhName": "",
  "iso2Code": ""
}, {
  "Country": "Djibouti",
  "TradeValue": 5364876,
  "TradeBalance": -5003449,
  "AnnualGrowth": 15,
  "WorldShare": 0,
  "EaseBusinessRank": 112,
  "Index": 125,
  "zhName": "吉布提",
  "iso2Code": "DJ"
}, {
  "Country": "Armenia",
  "TradeValue": 5319420,
  "TradeBalance": -2348198,
  "AnnualGrowth": 17,
  "WorldShare": 0,
  "EaseBusinessRank": 47,
  "Index": 126,
  "zhName": "亚美尼亚",
  "iso2Code": "AM"
}, {
  "Country": "Uganda",
  "TradeValue": 5207787,
  "TradeBalance": -3582903,
  "AnnualGrowth": 26,
  "WorldShare": 0,
  "EaseBusinessRank": 116,
  "Index": 127,
  "zhName": "乌干达",
  "iso2Code": "UG"
}, {
  "Country": "Mauritius",
  "TradeValue": 5179825,
  "TradeBalance": -3494999,
  "AnnualGrowth": 22,
  "WorldShare": 0,
  "EaseBusinessRank": 13,
  "Index": 128,
  "zhName": "毛里求斯",
  "iso2Code": "MU"
}, {
  "Country": "Zimbabwe",
  "TradeValue": 4933424,
  "TradeBalance": -2869953,
  "AnnualGrowth": 34,
  "WorldShare": 0,
  "EaseBusinessRank": 140,
  "Index": 129,
  "zhName": "津巴布韦",
  "iso2Code": "ZW"
}, {
  "Country": "Guinea",
  "TradeValue": 4901799,
  "TradeBalance": 2384256,
  "AnnualGrowth": 8,
  "WorldShare": 0,
  "EaseBusinessRank": 156,
  "Index": 130,
  "zhName": "几内亚",
  "iso2Code": "GN"
}, {
  "Country": "Burkina Faso",
  "TradeValue": 4709930,
  "TradeBalance": 350098,
  "AnnualGrowth": 13,
  "WorldShare": 0,
  "EaseBusinessRank": 151,
  "Index": 131,
  "zhName": "布基纳法索",
  "iso2Code": "BF"
}, {
  "Country": "Jamaica",
  "TradeValue": 4592121,
  "TradeBalance": -3568977,
  "AnnualGrowth": 13,
  "WorldShare": 0,
  "EaseBusinessRank": 71,
  "Index": 132,
  "zhName": "牙买加",
  "iso2Code": "JM"
}, {
  "Country": "Madagascar",
  "TradeValue": 4380344,
  "TradeBalance": -1661615,
  "AnnualGrowth": 36,
  "WorldShare": 0,
  "EaseBusinessRank": 161,
  "Index": 133,
  "zhName": "马达加斯加",
  "iso2Code": "MG"
}, {
  "Country": "Syrian Arab Republic",
  "TradeValue": 4374045,
  "TradeBalance": -3630463,
  "AnnualGrowth": 11,
  "WorldShare": 0,
  "EaseBusinessRank": 176,
  "Index": 134,
  "zhName": "",
  "iso2Code": ""
}, {
  "Country": "Haiti",
  "TradeValue": 4356040,
  "TradeBalance": -2972896,
  "AnnualGrowth": 6,
  "WorldShare": 0,
  "EaseBusinessRank": 179,
  "Index": 135,
  "zhName": "海地",
  "iso2Code": "HT"
}, {
  "Country": "Mali",
  "TradeValue": 4315681,
  "TradeBalance": -2249507,
  "AnnualGrowth": 19,
  "WorldShare": 0,
  "EaseBusinessRank": 148,
  "Index": 136,
  "zhName": "马里",
  "iso2Code": "ML"
}, {
  "Country": "Tajikistan",
  "TradeValue": 4217492,
  "TradeBalance": -2430807,
  "AnnualGrowth": 34,
  "WorldShare": 0,
  "EaseBusinessRank": 106,
  "Index": 137,
  "zhName": "塔吉克斯坦",
  "iso2Code": "TJ"
}, {
  "Country": "Papua New Guinea",
  "TradeValue": 4185086,
  "TradeBalance": 7423074,
  "AnnualGrowth": 9,
  "WorldShare": 0,
  "EaseBusinessRank": 120,
  "Index": 138,
  "zhName": "巴布亚新几内亚",
  "iso2Code": "PG"
}, {
  "Country": "Guyana",
  "TradeValue": 4146385,
  "TradeBalance": 97187,
  "AnnualGrowth": 67,
  "WorldShare": 0,
  "EaseBusinessRank": 134,
  "Index": 139,
  "zhName": "圭亚那",
  "iso2Code": "GY"
}, {
  "Country": "Mauritania",
  "TradeValue": 3860465,
  "TradeBalance": -593476,
  "AnnualGrowth": 35,
  "WorldShare": 0,
  "EaseBusinessRank": 152,
  "Index": 140,
  "zhName": "毛里塔尼亚",
  "iso2Code": "MR"
}, {
  "Country": "Afghanistan",
  "TradeValue": 3857785,
  "TradeBalance": -2381502,
  "AnnualGrowth": -18,
  "WorldShare": 0,
  "EaseBusinessRank": 173,
  "Index": 141,
  "zhName": "阿富汗",
  "iso2Code": "AF"
}, {
  "Country": "Benin",
  "TradeValue": 3188248,
  "TradeBalance": -2164068,
  "AnnualGrowth": 20,
  "WorldShare": 0,
  "EaseBusinessRank": 149,
  "Index": 142,
  "zhName": "贝宁",
  "iso2Code": "BJ"
}, {
  "Country": "Somalia",
  "TradeValue": 3172051,
  "TradeBalance": -3007364,
  "AnnualGrowth": 9,
  "WorldShare": 0,
  "EaseBusinessRank": 190,
  "Index": 143,
  "zhName": "索马里",
  "iso2Code": "SO"
}, {
  "Country": "Maldives",
  "TradeValue": 2580550,
  "TradeBalance": -2428969,
  "AnnualGrowth": 40,
  "WorldShare": 0,
  "EaseBusinessRank": 147,
  "Index": 144,
  "zhName": "马尔代夫",
  "iso2Code": "MV"
}, {
  "Country": "Montenegro",
  "TradeValue": 2504294,
  "TradeBalance": -2067243,
  "AnnualGrowth": 19,
  "WorldShare": 0,
  "EaseBusinessRank": 50,
  "Index": 145,
  "zhName": "黑山",
  "iso2Code": "ME"
}, {
  "Country": "Togo",
  "TradeValue": 2493138,
  "TradeBalance": -1423835,
  "AnnualGrowth": 15,
  "WorldShare": 0,
  "EaseBusinessRank": 97,
  "Index": 146,
  "zhName": "多哥",
  "iso2Code": "TG"
}, {
  "Country": "Congo",
  "TradeValue": 2351503,
  "TradeBalance": 10727,
  "AnnualGrowth": 23,
  "WorldShare": 0,
  "EaseBusinessRank": 180,
  "Index": 147,
  "zhName": "",
  "iso2Code": ""
}, {
  "Country": "Fiji",
  "TradeValue": 2115650,
  "TradeBalance": -1300314,
  "AnnualGrowth": 22,
  "WorldShare": 0,
  "EaseBusinessRank": 102,
  "Index": 148,
  "zhName": "斐济",
  "iso2Code": "FJ"
}, {
  "Country": "Gabon",
  "TradeValue": 2032457,
  "TradeBalance": 4512076,
  "AnnualGrowth": -8,
  "WorldShare": 0,
  "EaseBusinessRank": 169,
  "Index": 149,
  "zhName": "加蓬",
  "iso2Code": "GA"
}, {
  "Country": "Rwanda",
  "TradeValue": 2021462,
  "TradeBalance": -1630660,
  "AnnualGrowth": 37,
  "WorldShare": 0,
  "EaseBusinessRank": 38,
  "Index": 150,
  "zhName": "卢旺达",
  "iso2Code": "RW"
}, {
  "Country": "Eswatini",
  "TradeValue": 1762381,
  "TradeBalance": 483185,
  "AnnualGrowth": 29,
  "WorldShare": 0,
  "EaseBusinessRank": 121,
  "Index": 151,
  "zhName": "",
  "iso2Code": ""
}, {
  "Country": "Barbados",
  "TradeValue": 1673621,
  "TradeBalance": -1323448,
  "AnnualGrowth": 11,
  "WorldShare": 0,
  "EaseBusinessRank": 128,
  "Index": 152,
  "zhName": "巴巴多斯",
  "iso2Code": "BB"
}, {
  "Country": "Niger",
  "TradeValue": 1639924,
  "TradeBalance": -690123,
  "AnnualGrowth": 22,
  "WorldShare": 0,
  "EaseBusinessRank": 132,
  "Index": 153,
  "zhName": "尼日尔",
  "iso2Code": "NE"
}, {
  "Country": "Lesotho",
  "TradeValue": 1611409,
  "TradeBalance": -604368,
  "AnnualGrowth": 30,
  "WorldShare": 0,
  "EaseBusinessRank": 122,
  "Index": 154,
  "zhName": "莱索托",
  "iso2Code": "LS"
}, {
  "Country": "Gambia",
  "TradeValue": 1551752,
  "TradeBalance": -1422393,
  "AnnualGrowth": 10,
  "WorldShare": 0,
  "EaseBusinessRank": 155,
  "Index": 155,
  "zhName": "冈比亚",
  "iso2Code": "GM"
}, {
  "Country": "Malawi",
  "TradeValue": 1544037,
  "TradeBalance": -628295,
  "AnnualGrowth": 20,
  "WorldShare": 0,
  "EaseBusinessRank": 109,
  "Index": 156,
  "zhName": "马拉维",
  "iso2Code": "MW"
}, {
  "Country": "Sierra Leone",
  "TradeValue": 1498137,
  "TradeBalance": -586692,
  "AnnualGrowth": 33,
  "WorldShare": 0,
  "EaseBusinessRank": 163,
  "Index": 157,
  "zhName": "塞拉利昂",
  "iso2Code": "SL"
}, {
  "Country": "Saint Lucia",
  "TradeValue": 1430857,
  "TradeBalance": -1388999,
  "AnnualGrowth": 24,
  "WorldShare": 0,
  "EaseBusinessRank": 93,
  "Index": 158,
  "zhName": "",
  "iso2Code": ""
}, {
  "Country": "Suriname",
  "TradeValue": 1240528,
  "TradeBalance": 288406,
  "AnnualGrowth": 12,
  "WorldShare": 0,
  "EaseBusinessRank": 162,
  "Index": 159,
  "zhName": "苏里南",
  "iso2Code": "SR"
}, {
  "Country": "Antigua and Barbuda",
  "TradeValue": 1234724,
  "TradeBalance": -1042692,
  "AnnualGrowth": 63,
  "WorldShare": 0,
  "EaseBusinessRank": 113,
  "Index": 160,
  "zhName": "安提瓜和巴布达",
  "iso2Code": "AG"
}, {
  "Country": "Bhutan",
  "TradeValue": 1100397,
  "TradeBalance": -742982,
  "AnnualGrowth": 34,
  "WorldShare": 0,
  "EaseBusinessRank": 89,
  "Index": 161,
  "zhName": "不丹",
  "iso2Code": "BT"
}, {
  "Country": "Belize",
  "TradeValue": 1057442,
  "TradeBalance": -799963,
  "AnnualGrowth": 34,
  "WorldShare": 0,
  "EaseBusinessRank": 135,
  "Index": 162,
  "zhName": "伯利兹",
  "iso2Code": "BZ"
}, {
  "Country": "Cabo Verde",
  "TradeValue": 880827,
  "TradeBalance": -754472,
  "AnnualGrowth": 9,
  "WorldShare": 0,
  "EaseBusinessRank": 137,
  "Index": 163,
  "zhName": "",
  "iso2Code": ""
}, {
  "Country": "Equatorial Guinea",
  "TradeValue": 835629,
  "TradeBalance": 4040315,
  "AnnualGrowth": -29,
  "WorldShare": 0,
  "EaseBusinessRank": 178,
  "Index": 164,
  "zhName": "",
  "iso2Code": ""
}, {
  "Country": "Timor-Leste",
  "TradeValue": 797394,
  "TradeBalance": -523931,
  "AnnualGrowth": 28,
  "WorldShare": 0,
  "EaseBusinessRank": 181,
  "Index": 165,
  "zhName": "",
  "iso2Code": ""
}, {
  "Country": "Chad",
  "TradeValue": 741803,
  "TradeBalance": 1484400,
  "AnnualGrowth": -9,
  "WorldShare": 0,
  "EaseBusinessRank": 182,
  "Index": 166,
  "zhName": "乍得",
  "iso2Code": "TD"
}, {
  "Country": "Dominica",
  "TradeValue": 649650,
  "TradeBalance": -620412,
  "AnnualGrowth": 233,
  "WorldShare": 0,
  "EaseBusinessRank": 111,
  "Index": 167,
  "zhName": "多米尼加",
  "iso2Code": "DO"
}, {
  "Country": "Seychelles",
  "TradeValue": 616353,
  "TradeBalance": 52016,
  "AnnualGrowth": -12,
  "WorldShare": 0,
  "EaseBusinessRank": 100,
  "Index": 168,
  "zhName": "塞舌尔",
  "iso2Code": "SC"
}, {
  "Country": "Burundi",
  "TradeValue": 603983,
  "TradeBalance": -528407,
  "AnnualGrowth": 13,
  "WorldShare": 0,
  "EaseBusinessRank": 166,
  "Index": 169,
  "zhName": "布隆迪",
  "iso2Code": "BI"
}, {
  "Country": "Solomon Islands",
  "TradeValue": 467480,
  "TradeBalance": 39884,
  "AnnualGrowth": 31,
  "WorldShare": 0,
  "EaseBusinessRank": 136,
  "Index": 170,
  "zhName": "",
  "iso2Code": ""
}, {
  "Country": "Grenada",
  "TradeValue": 446676,
  "TradeBalance": -411513,
  "AnnualGrowth": 13,
  "WorldShare": 0,
  "EaseBusinessRank": 146,
  "Index": 171,
  "zhName": "",
  "iso2Code": ""
}, {
  "Country": "Comoros",
  "TradeValue": 442884,
  "TradeBalance": -407890,
  "AnnualGrowth": 65,
  "WorldShare": 0,
  "EaseBusinessRank": 160,
  "Index": 172,
  "zhName": "科摩罗",
  "iso2Code": "KM"
}, {
  "Country": "South Sudan",
  "TradeValue": 406013,
  "TradeBalance": 71180,
  "AnnualGrowth": -14,
  "WorldShare": 0,
  "EaseBusinessRank": 185,
  "Index": 173,
  "zhName": "南苏丹",
  "iso2Code": "SS"
}, {
  "Country": "Guinea-Bissau",
  "TradeValue": 395492,
  "TradeBalance": -213903,
  "AnnualGrowth": 24,
  "WorldShare": 0,
  "EaseBusinessRank": 174,
  "Index": 174,
  "zhName": "",
  "iso2Code": ""
}, {
  "Country": "Saint Vincent and the Grenadines",
  "TradeValue": 371946,
  "TradeBalance": -273578,
  "AnnualGrowth": 81,
  "WorldShare": 0,
  "EaseBusinessRank": 130,
  "Index": 175,
  "zhName": "",
  "iso2Code": ""
}, {
  "Country": "Samoa",
  "TradeValue": 370236,
  "TradeBalance": -341244,
  "AnnualGrowth": 19,
  "WorldShare": 0,
  "EaseBusinessRank": 98,
  "Index": 176,
  "zhName": "",
  "iso2Code": ""
}, {
  "Country": "Vanuatu",
  "TradeValue": 331278,
  "TradeBalance": -48015,
  "AnnualGrowth": 32,
  "WorldShare": 0,
  "EaseBusinessRank": 107,
  "Index": 177,
  "zhName": "",
  "iso2Code": ""
}, {
  "Country": "Central African Republic",
  "TradeValue": 262499,
  "TradeBalance": -176260,
  "AnnualGrowth": 4,
  "WorldShare": 0,
  "EaseBusinessRank": 184,
  "Index": 178,
  "zhName": "中非共和国",
  "iso2Code": "CF"
}, {
  "Country": "Saint Kitts and Nevis",
  "TradeValue": 231548,
  "TradeBalance": -164635,
  "AnnualGrowth": -13,
  "WorldShare": 0,
  "EaseBusinessRank": 139,
  "Index": 179,
  "zhName": "",
  "iso2Code": ""
}, {
  "Country": "Tonga",
  "TradeValue": 219260,
  "TradeBalance": -203398,
  "AnnualGrowth": 24,
  "WorldShare": 0,
  "EaseBusinessRank": 103,
  "Index": 180,
  "zhName": "汤加",
  "iso2Code": "TO"
}, {
  "Country": "Eritrea",
  "TradeValue": 210751,
  "TradeBalance": 254067,
  "AnnualGrowth": -26,
  "WorldShare": 0,
  "EaseBusinessRank": 189,
  "Index": 181,
  "zhName": "厄立特里亚",
  "iso2Code": "ER"
}, {
  "Country": "Kiribati",
  "TradeValue": 167256,
  "TradeBalance": -64561,
  "AnnualGrowth": 16,
  "WorldShare": 0,
  "EaseBusinessRank": 164,
  "Index": 182,
  "zhName": "",
  "iso2Code": ""
}, {
  "Country": "Micronesia, Federated States of",
  "TradeValue": 131461,
  "TradeBalance": 68902,
  "AnnualGrowth": -8,
  "WorldShare": 0,
  "EaseBusinessRank": 158,
  "Index": 183,
  "zhName": "",
  "iso2Code": ""
}, {
  "Country": "Palau",
  "TradeValue": 124867,
  "TradeBalance": -119178,
  "AnnualGrowth": 29,
  "WorldShare": 0,
  "EaseBusinessRank": 145,
  "Index": 184,
  "zhName": "",
  "iso2Code": ""
}, {
  "Country": "Sao Tome and Principe",
  "TradeValue": 124565,
  "TradeBalance": -93109,
  "AnnualGrowth": 10,
  "WorldShare": 0,
  "EaseBusinessRank": 170,
  "Index": 185,
  "zhName": "圣多美和普林西比",
  "iso2Code": "ST"
}]
